unit_syntax/__init__.py
unit_syntax/__main__.py
unit_syntax/import_hook.py
unit_syntax/ipython.py
unit_syntax/parser.py
unit_syntax/transform.py
unit_syntax-0.3.1.dist-info/METADATA
unit_syntax-0.3.1.dist-info/WHEEL
unit_syntax-0.3.1.dist-info/RECORD
