Metadata-Version: 2.1
Name: unit-syntax
Version: 0.3.1
Summary: Physical unit literals for Jupyter and IPython
Home-page: https://github.com/ahupp/unit-syntax
Author: Adam Hupp
Author-email: adam@hupp.org
Requires-Python: >=3.8,<4
Classifier: Programming Language :: Python :: 3
Classifier: Programming Language :: Python :: 3.8
Classifier: Programming Language :: Python :: 3.9
Classifier: Programming Language :: Python :: 3.10
Classifier: Programming Language :: Python :: 3.11
Requires-Dist: Pint (>0.20)
Requires-Dist: import-transforms (>=0.6,<0.7)
Requires-Dist: ipython (>=7)
Requires-Dist: pegen (>=0.2,<0.3)
Project-URL: Repository, https://github.com/ahupp/unit-syntax
